{
  "difficulty": "Easy",
  "frontendId": "0175",
  "language": "MS SQL Server",
  "leetcodeUrl": "https://leetcode.com/problems/combine-two-tables/",
  "memory": "0B",
  "rawFrontendId": "175",
  "runtime": "593 ms",
  "status": "Accepted",
  "submissionId": "1991164666",
  "submissionUrl": "https://leetcode.com/submissions/detail/1991164666/",
  "submittedAt": "2026-04-29T16:25:43+00:00",
  "syncedAt": "2026-05-14T04:55:43.632021+00:00",
  "title": "Combine Two Tables",
  "titleSlug": "combine-two-tables",
  "topicTags": [
    {
      "name": "Database",
      "slug": "database"
    }
  ]
}
